{"afk":"Lunch!","active":false,"address":"97.73.96.92","age":"very young","alignment":8,"arm":"none","bandage":0,"beard":"none","birth":"2013-10-11T10:09:53","complexion":"sun-kissed skin","constitution":2,"copper":2,"creation":"2013-11-01T01:40:42","dexterity":2,"drinkstats":0,"eatstats":0,"email":"","experience":0,"eyes":"glowing <font color=red>red</font> eyes","face":"a cute face","familyname":"Nasling aka \"Haunt Gunther\"","fightable":false,"fightingwho":"","fysically":0,"god":"DEFAULT_USER","guild":"haunt","hair":"and a grumpy demeanor","heehaws":0,"height":"bright red-haired","intelligence":2,"jumpmana":1,"jumpmove":1,"jumpvital":1,"lastlogin":"2024-03-17T13:30:37","leg":"none","manastats":0,"maxmana":118,"maxmove":500,"maxvital":118,"mentally":0,"movementstats":1000,"name":"Aaron","ooc":false,"owner":"Victoria","practises":0,"punishment":0,"race":"haunt","realname":"","room":4448,"rrribbits":0,"sex":"male","sleep":false,"strength":2,"title":"<img src=\"https://i.imgur.com/ref5cBU.jpg\" />","training":0,"visible":true,"vitals":0,"whimpy":"AT_DEATH","width":"chubby","wisdom":2}
